setup.py
kyper/__init__.py
kyper/_compat.py
kyper/_exthook.py
kyper.egg-info/PKG-INFO
kyper.egg-info/SOURCES.txt
kyper.egg-info/dependency_links.txt
kyper.egg-info/pbr.json
kyper.egg-info/top_level.txt