Metadata-Version: 1.0
Name: kyper
Version: 0.0.2
Summary: Kyper Root Package
Home-page: UNKNOWN
Author: Kyper Developers
Author-email: developers@kyperdata.com
License: UNKNOWN
Platform: UNKNOWN
